{
  "frobou-doc-go": {
    "username": "frobou",
    "service": "github",
    "destination": "outra_pasta",
    "protocol": "https",
    "ssh-key": false
  },
  "ApiTest": {
    "username": "frobou",
    "ssh-key": false,
    "protocol": "ssh",
    "destination": "ApiTest",
    "service": "bitbucket",
    "password": "bmFvdGVt"
  },
  "ispti_dns": {
    "username": "efepimenta",
    "service": "bitbucket",
    "password": "key",
    "ssh-key": false,
    "protocol": "ssh"
  },
  "frobou-db-connect": {
    "username": "frobou",
    "service": "github",
    "ssh-key": false,
    "protocol": "ssh"
  }
}